simple_ocrmypdf/__init__.py
simple_ocrmypdf/about.py
simple_ocrmypdf/desktop.py
simple_ocrmypdf/program.py
simple_ocrmypdf/icons/logo.png
simple_ocrmypdf/modules/__init__.py
simple_ocrmypdf/modules/wabout.py
simple_ocrmypdf-0.1.1.dist-info/licenses/LICENSE
simple_ocrmypdf-0.1.1.dist-info/METADATA
simple_ocrmypdf-0.1.1.dist-info/WHEEL
simple_ocrmypdf-0.1.1.dist-info/entry_points.txt
simple_ocrmypdf-0.1.1.dist-info/top_level.txt
simple_ocrmypdf-0.1.1.dist-info/RECORD
